{"kind":"youtube#videoListResponse","etag":"YM2E6nFNCJ90oNZpMf3grRhHdjs","items":[{"kind":"youtube#video","etag":"npbOdlghd_MEmrSB34c_hg2lbQU","id":"-ekSeKLRpiM","snippet":{"publishedAt":"2019-10-15T10:49:57Z","channelId":"UCRJoKzF5oFqC7SiA9AUleYw","title":"Parte 3 Lindbergue Tratamento precoce antes dos 6 anos  IvoBlu","description":"Palestra de Lindbergue Mariano Colletes Alves, fundador do Ivo Brasil e Ivo Itália.\nEncontro do Ivo Blumenau\nOrtopedia Funcional Dos Maxilares\nhttps://ivoblu.blogspot.com/","thumbnails":{"default":{"url":"https://i.ytimg.com/vi/-ekSeKLRpiM/default.jpg","width":120,"height":90},"medium":{"url":"https://i.ytimg.com/vi/-ekSeKLRpiM/mqdefault.jpg","width":320,"height":180},"high":{"url":"https://i.ytimg.com/vi/-ekSeKLRpiM/hqdefault.jpg","width":480,"height":360},"standard":{"url":"https://i.ytimg.com/vi/-ekSeKLRpiM/sddefault.jpg","width":640,"height":480},"maxres":{"url":"https://i.ytimg.com/vi/-ekSeKLRpiM/maxresdefault.jpg","width":1280,"height":720}},"channelTitle":"Dr Rafael Ferreira","tags":["Ortopedia funcional dos Maxilares","Reabilitação neuroclusal","Tratamento precoce","tratamento dentes antes 6 anos","Ortodontia","ivoblu"],"categoryId":"27","liveBroadcastContent":"none","localized":{"title":"Parte 3 Lindbergue Tratamento precoce antes dos 6 anos  IvoBlu","description":"Palestra de Lindbergue Mariano Colletes Alves, fundador do Ivo Brasil e Ivo Itália.\nEncontro do Ivo Blumenau\nOrtopedia Funcional Dos Maxilares\nhttps://ivoblu.blogspot.com/"},"defaultAudioLanguage":"pt-BR"},"contentDetails":{"duration":"PT33M8S","dimension":"2d","definition":"hd","caption":"false","licensedContent":false,"contentRating":{},"projection":"rectangular"},"status":{"uploadStatus":"processed","privacyStatus":"public","license":"youtube","embeddable":true,"publicStatsViewable":true,"madeForKids":false},"statistics":{"viewCount":"85","likeCount":"5","dislikeCount":"0","favoriteCount":"0","commentCount":"1"},"topicDetails":{"topicCategories":["https://en.wikipedia.org/wiki/Knowledge"]}}],"pageInfo":{"totalResults":1,"resultsPerPage":1}}