{"kind":"youtube#videoListResponse","etag":"5z2t56STDwIpwgk_ByRN9MkZBT0","items":[{"kind":"youtube#video","etag":"XrHzrmXsik3Yd9AHdgzRcTMJXzU","id":"m0kqP1ZDgTY","snippet":{"publishedAt":"2020-11-28T22:15:02Z","channelId":"UCpMk4QnCk9uzGjbM9FcmreQ","title":"28/11  Jogo Aberto - Tratamento precoce para COVID-19 - Entrevista Dr. Laércio Cecconello","description":"","thumbnails":{"default":{"url":"https://i.ytimg.com/vi/m0kqP1ZDgTY/default.jpg","width":120,"height":90},"medium":{"url":"https://i.ytimg.com/vi/m0kqP1ZDgTY/mqdefault.jpg","width":320,"height":180},"high":{"url":"https://i.ytimg.com/vi/m0kqP1ZDgTY/hqdefault.jpg","width":480,"height":360},"standard":{"url":"https://i.ytimg.com/vi/m0kqP1ZDgTY/sddefault.jpg","width":640,"height":480},"maxres":{"url":"https://i.ytimg.com/vi/m0kqP1ZDgTY/maxresdefault.jpg","width":1280,"height":720}},"channelTitle":"Tarobá Jornalismo","tags":["Primeira Hora","Jornal Tarobá","Tarobá Esporte","Tempo Quente","Brasil Urgente","Ponto de Vista","Jogo Aberto","Tarobá Rural","Jean Peretto","Caio","Luiz Haab","Dany Wolff","Vagner Krazt","Patrícia Sonsin","Taísa Kissel","Sirlei Benetti","Oziel Luiz","Batatinha","Diogo Hutt","Cid Ribeiro","Fernando Brevilheri","reportagem","Foz do Iguaçú","Cascavel","Londrina","Regiao","Matéria tv","Reportagem de tv","notícia","Jornal","Bans","Tv Tarobá","Educação","Saúde","Policia","Programa Policial","Jornalismo","Política"],"categoryId":"25","liveBroadcastContent":"none","localized":{"title":"28/11  Jogo Aberto - Tratamento precoce para COVID-19 - Entrevista Dr. Laércio Cecconello","description":""}},"contentDetails":{"duration":"PT30M27S","dimension":"2d","definition":"hd","caption":"false","licensedContent":false,"contentRating":{},"projection":"rectangular"},"status":{"uploadStatus":"processed","privacyStatus":"public","license":"youtube","embeddable":true,"publicStatsViewable":false,"madeForKids":false},"statistics":{"viewCount":"2280","likeCount":"154","dislikeCount":"3","favoriteCount":"0","commentCount":"10"},"topicDetails":{"topicCategories":["https://en.wikipedia.org/wiki/Society"]}}],"pageInfo":{"totalResults":1,"resultsPerPage":1}}