{"kind":"youtube#videoListResponse","etag":"oOaPVizKpx5cjXBwawzCS6iwSjg","items":[{"kind":"youtube#video","etag":"mp1LvCkf1yeypedqxj6l2o4NTJM","id":"Po-3PxdY0d0","snippet":{"publishedAt":"2021-01-14T14:19:17Z","channelId":"UCdn_CLVvxtRmChHNJyv-dgQ","title":"Agora GRAVÍSSIMO! Suspensão de Tratamento Precoce do COVID pedido pelo PSOL. Presidente averiguando","description":"AJUDE o canal a \"sobreviver\" , faça qualquer doação \nhttps://www.paypal.com/donate/?cmd=_s-xclick&hosted_button_id=GHAJWPQVL2JYL\nInscreva-se no canal pra ajudar o Brasil a melhorar\nSiga o canal no TWITTER @3_bolsonaro","thumbnails":{"default":{"url":"https://i.ytimg.com/vi/Po-3PxdY0d0/default.jpg","width":120,"height":90},"medium":{"url":"https://i.ytimg.com/vi/Po-3PxdY0d0/mqdefault.jpg","width":320,"height":180},"high":{"url":"https://i.ytimg.com/vi/Po-3PxdY0d0/hqdefault.jpg","width":480,"height":360},"standard":{"url":"https://i.ytimg.com/vi/Po-3PxdY0d0/sddefault.jpg","width":640,"height":480},"maxres":{"url":"https://i.ytimg.com/vi/Po-3PxdY0d0/maxresdefault.jpg","width":1280,"height":720}},"channelTitle":"Bolsonaro Ja 3","tags":["BOLSONARO","JA","lula","dilma","trump","china","virus","pandemia","epidemia","doria","hidrocloroquina","oms","moro","mandeta"],"categoryId":"25","liveBroadcastContent":"none","localized":{"title":"Agora GRAVÍSSIMO! Suspensão de Tratamento Precoce do COVID pedido pelo PSOL. Presidente averiguando","description":"AJUDE o canal a \"sobreviver\" , faça qualquer doação \nhttps://www.paypal.com/donate/?cmd=_s-xclick&hosted_button_id=GHAJWPQVL2JYL\nInscreva-se no canal pra ajudar o Brasil a melhorar\nSiga o canal no TWITTER @3_bolsonaro"},"defaultAudioLanguage":"pt"},"contentDetails":{"duration":"PT4M12S","dimension":"2d","definition":"hd","caption":"false","licensedContent":false,"contentRating":{},"projection":"rectangular"},"status":{"uploadStatus":"processed","privacyStatus":"public","license":"youtube","embeddable":true,"publicStatsViewable":true,"madeForKids":false},"statistics":{"viewCount":"18","likeCount":"5","dislikeCount":"1","favoriteCount":"0","commentCount":"0"},"topicDetails":{"topicCategories":["https://en.wikipedia.org/wiki/Politics","https://en.wikipedia.org/wiki/Society"]}}],"pageInfo":{"totalResults":1,"resultsPerPage":1}}